odoo/addons/sale_order_import_ubl_customer_free_ref/README.rst
odoo/addons/sale_order_import_ubl_customer_free_ref/__init__.py
odoo/addons/sale_order_import_ubl_customer_free_ref/__manifest__.py
odoo/addons/sale_order_import_ubl_customer_free_ref/i18n/sale_order_import_ubl_customer_free_ref.pot
odoo/addons/sale_order_import_ubl_customer_free_ref/readme/CONTRIBUTORS.rst
odoo/addons/sale_order_import_ubl_customer_free_ref/readme/DESCRIPTION.rst
odoo/addons/sale_order_import_ubl_customer_free_ref/static/description/icon.png
odoo/addons/sale_order_import_ubl_customer_free_ref/static/description/index.html
odoo/addons/sale_order_import_ubl_customer_free_ref/tests/__init__.py
odoo/addons/sale_order_import_ubl_customer_free_ref/tests/test_ubl_order_import.py
odoo/addons/sale_order_import_ubl_customer_free_ref/tests/files/UBL-Order-2.0-Example.xml
odoo/addons/sale_order_import_ubl_customer_free_ref/tests/files/UBL-Order-2.1-Example.xml
odoo/addons/sale_order_import_ubl_customer_free_ref/wizard/__init__.py
odoo/addons/sale_order_import_ubl_customer_free_ref/wizard/sale_order_import.py
odoo14_addon_sale_order_import_ubl_customer_free_ref-14.0.1.1.0.dist-info/METADATA
odoo14_addon_sale_order_import_ubl_customer_free_ref-14.0.1.1.0.dist-info/WHEEL
odoo14_addon_sale_order_import_ubl_customer_free_ref-14.0.1.1.0.dist-info/top_level.txt
odoo14_addon_sale_order_import_ubl_customer_free_ref-14.0.1.1.0.dist-info/RECORD
