Metadata-Version: 2.1
Name: odoo14-addon-sale-order-import-ubl-customer-free-ref
Version: 14.0.1.1.0
Summary: Extract CustomerReference from sale UBL
Home-page: https://github.com/OCA/edi
Author: Camptocamp SA, Odoo Community Association (OCA)
Author-email: support@odoo-community.org
License: AGPL-3
Platform: UNKNOWN
Classifier: Programming Language :: Python
Classifier: Framework :: Odoo
Classifier: Framework :: Odoo :: 14.0
Classifier: License :: OSI Approved :: GNU Affero General Public License v3
Requires-Python: >=3.6
Requires-Dist: odoo14-addon-sale-order-customer-free-ref
Requires-Dist: odoo14-addon-sale-order-import-ubl
Requires-Dist: odoo (<14.1dev,>=14.0a)
